glirel/__init__.py
glirel/model.py
glirel/spacy_integration.py
glirel/test_model.py
glirel/test_spacy_integration.py
glirel/modules/___init__.py
glirel/modules/base.py
glirel/modules/custom_tokenizers.py
glirel/modules/data_proc.py
glirel/modules/evaluator.py
glirel/modules/layers.py
glirel/modules/loss_functions.py
glirel/modules/rel_rep.py
glirel/modules/run_evaluation.py
glirel/modules/span_rep.py
glirel/modules/test_rel_rep.py
glirel/modules/test_token_rep.py
glirel/modules/test_transformer_embeddings.py
glirel/modules/token_rep.py
glirel/modules/transformer_embeddings.py
glirel/modules/utils.py
glirel-1.2.1.dist-info/METADATA
glirel-1.2.1.dist-info/WHEEL
glirel-1.2.1.dist-info/top_level.txt
glirel-1.2.1.dist-info/RECORD
