Metadata-Version: 2.4
Name: glirel
Version: 1.2.1
Summary: Generalist model for Relation Extraction (Extract any relation types from texts)
Author: Jack Boylan, Urchade Zaratiana
Maintainer: Jack Boylan
License: Apache-2.0
Project-URL: Homepage, https://github.com/jackboyla/GLiREL
Keywords: named-entity-recognition,ner,data-science,natural-language-processing,artificial-intelligence,nlp,machine-learning,transformers
Requires-Python: >=3.8
Requires-Dist: torch
Requires-Dist: transformers
Requires-Dist: huggingface_hub
Requires-Dist: seqeval
Requires-Dist: tqdm
Requires-Dist: datasets
